timed_count/__init__.py
timed_count/cls_timed_count.py
timed_count/timed_count.py
timed_count-2.0.0.dist-info/LICENSE
timed_count-2.0.0.dist-info/METADATA
timed_count-2.0.0.dist-info/WHEEL
timed_count-2.0.0.dist-info/RECORD
