Metadata-Version: 2.1
Name: timed-count
Version: 2.0.0
Summary: timed-count provides an iterator that delays each iteration by a specified time period. It can be used to repeatedly execute code at a precise frequency.
Home-page: https://github.com/morefigs/timed-count
Author: morefigs
Requires-Python: >=3.7,<4.0
Classifier: Programming Language :: Python :: 3
Classifier: Programming Language :: Python :: 3.7
Classifier: Programming Language :: Python :: 3.8
Classifier: Programming Language :: Python :: 3.9
Classifier: Programming Language :: Python :: 3.10
Classifier: Programming Language :: Python :: 3.11
Classifier: Programming Language :: Python :: 3.12
Requires-Dist: stoppy (>=1.0.5,<2.0.0)
